[{"model": "datalin.technology", "pk": 1, "fields": {"short_name": "Netezza", "name": "Netezza", "provider": "IBM"}}, {"model": "datalin.technology", "pk": 2, "fields": {"short_name": "BO", "name": "Business Objects", "provider": "SAP"}}, {"model": "datalin.technology", "pk": 3, "fields": {"short_name": "MS SQL", "name": "SQL Server", "provider": "Microsoft"}}, {"model": "datalin.technology", "pk": 4, "fields": {"short_name": "SSRS", "name": "SQL Server Reporting Services", "provider": "Microsoft"}}, {"model": "datalin.technology", "pk": 5, "fields": {"short_name": "SSAS", "name": "SQL Server Analysis Services", "provider": "Microsoft"}}, {"model": "datalin.technology", "pk": 6, "fields": {"short_name": "Oracle DB", "name": "Oracle Database", "provider": "Oracle"}}, {"model": "datalin.entity", "pk": 3, "fields": {"short_name": "DB", "name": "Database", "description": null, "technology": 1}}, {"model": "datalin.entity", "pk": 4, "fields": {"short_name": "T", "name": "Table", "description": null, "technology": 1}}, {"model": "datalin.entity", "pk": 5, "fields": {"short_name": "Unx", "name": "Universe", "description": null, "technology": 2}}, {"model": "datalin.entity", "pk": 6, "fields": {"short_name": "VW", "name": "View", "description": null, "technology": 1}}, {"model": "datalin.entity", "pk": 10, "fields": {"short_name": "DB", "name": "Database", "description": null, "technology": 3}}, {"model": "datalin.entity", "pk": 11, "fields": {"short_name": "T", "name": "Table", "description": null, "technology": 3}}, {"model": "datalin.entity", "pk": 12, "fields": {"short_name": "VW", "name": "View", "description": null, "technology": 3}}]